cachefunc/__init__.py
cachefunc/cache/base.py
cachefunc/cache/dict_cache.py
cachefunc/cache/redis_cache.py
cachefunc/log.py
cachefunc/main.py
cachefunc-0.2.6.dist-info/METADATA
cachefunc-0.2.6.dist-info/WHEEL
cachefunc-0.2.6.dist-info/RECORD
